{
  "마멘토": {
    "main_url": "https://www.mamentor.co.kr",
    "login_btn_sel": "",
    "write_url": "https://www.mamentor.co.kr/bbs/write.php?bo_table=place_ad",
    "popup_sel": ".hd_pops_reject, .btn_pops_close",
    "id_sel": "#ol_id, input[name='mb_id'], input[placeholder*='아이디']",
    "pw_sel": "#ol_pw, input[name='mb_password'], input[type='password']",
    "btn_sel": ".btn_login, input[type='submit'][value*='로그인'], button[type='submit']",
    "title_sel": "#wr_subject",
    "editor_type": "ckeditor4",
    "editor_sel": "#wr_content",
    "submit_sel": "#btn_submit",
    "success_pat": "wr_id=",
    "cat_sel": "select[name='ca_name']",
    "link1_sel": "#wr_link1",
    "link2_sel": "#wr_link2",
    "color": "#3B82F6",
    "enabled": true
  },
  "투잡커넥트": {
    "main_url": "https://www.tojobcn.com",
    "login_url": "https://www.tojobcn.com/bbs/login.php",
    "login_btn_sel": "",
    "write_url": "https://www.tojobcn.com/bbs/write.php?bo_table=order",
    "popup_sel": "",
    "id_sel": "input[name='mb_id']",
    "pw_sel": "input[name='mb_password']",
    "btn_sel": "button[type='submit'], input[type='submit'][value*='로그인']",
    "title_sel": "#wr_subject",
    "editor_type": "smarteditor2",
    "editor_sel": "#wr_content",
    "submit_sel": "#btn_submit",
    "success_pat": "wr_id=",
    "cat_sel": "select[name='ca_name']",
    "cat_default": "업체홍보",
    "link1_sel": "#wr_link1",
    "link2_sel": "#wr_link2",
    "color": "#22C55E",
    "enabled": true
  },
  "비즈모아": {
    "main_url": "https://www.bizmoa.co.kr",
    "login_btn_sel": "",
    "write_url": "",
    "popup_sel": "#dismiss-button",
    "id_sel": "#id",
    "pw_sel": "#pw",
    "btn_sel": ".btn_login",
    "title_sel": "#wr_subject",
    "editor_type": "smarteditor2",
    "editor_sel": "",
    "submit_sel": "#btn_submit",
    "success_pat": "wr_id=",
    "cat_sel": "",
    "link1_sel": "",
    "link2_sel": "",
    "color": "#F59E0B",
    "enabled": true
  },
  "셀프모아": {
    "main_url": "https://www.selfmoa.com",
    "login_btn_sel": "",
    "write_url": "",
    "popup_sel": "#dismiss-button",
    "id_sel": "input[name='mb_id'], #outlogin_mb_id",
    "pw_sel": "input[name='mb_password'], #outlogin_mb_password",
    "btn_sel": "button[type='submit'].btn-navy, button[type='submit']",
    "title_sel": "#wr_subject",
    "editor_type": "smarteditor2",
    "editor_sel": "",
    "cat_sel": "select[name='ca_name']",
    "submit_sel": "#btn_submit",
    "success_pat": "wr_id=",
    "link1_sel": "",
    "link2_sel": "",
    "enabled": true
  },
  "아이보스": {
    "main_url": "https://www.i-boss.co.kr/ab-login",
    "login_btn_sel": "",
    "write_url": "https://www.i-boss.co.kr/ab-2988",
    "popup_sel": "",
    "id_sel": "input[name='member_id'], input[placeholder*='아이디'], input[placeholder*='이메일']",
    "pw_sel": "input[name='member_pw'], input[type='password']",
    "btn_sel": "button[type='submit'], .btn-login, .btn-submit",
    "title_sel": "#subject",
    "editor_type": "summernote",
    "editor_sel": ".note-editable",
    "cat_sel": ".custom-select-display",
    "cat_type": "custom_select",
    "cat_options": {
      "B": "블로그",
      "C": "카페",
      "A": "인스타그램",
      "D": "유튜브",
      "S": "SNS",
      "J": "스토어",
      "U": "언론홍보",
      "W": "SEO",
      "F": "지도",
      "G": "포스팅",
      "E": "체험단",
      "H": "인플루언서",
      "O": "숏폼",
      "N": "PPL",
      "Z": "기타"
    },
    "submit_sel": "input[name='submit_OK']",
    "success_pat": "ab-",
    "link1_sel": "",
    "link2_sel": "",
    "field_map": {
      "company": "etc_1",
      "manager": "etc_4",
      "contact": "phone_2",
      "email": "etc_5",
      "nate": "etc_2",
      "kakao": "etc_3"
    },
    "color": "#EF4444",
    "enabled": true
  }
}